[
  {
    "id": "medusa",
    "copy-from": "pistol_revolver",
    "looks_like": "sw_619",
    "type": "GUN",
    "name": { "str": "multi-caliber revolver" },
    "description": "Officially, this revolver can fit 25 different calibers in its chambers, but this comes at the cost of having a rather finicky reloading process and somewhat reduced accuracy. Only a few hundred of these were made before the company went bankrupt, and somehow this one has ended up in your hands.",
    "ascii_picture": "redhawk",
    "variant_type": "gun",
    "variants": [
      {
        "id": "medusa",
        "name": { "str": "M47 Medusa" },
        "description": "Officially, this revolver can fit 25 different calibers in its chambers, but this comes at the cost of having a rather finicky reloading process and somewhat reduced accuracy. Only a few hundred of these were made before the company went bankrupt, and somehow this one has ended up in your hands."
      }
    ],
    "weight": "1333 g",
    "volume": "450 ml",
    "longest_side": "25 cm",
    "barrel_length": "152 mm",
    "price": 861000,
    "price_postapoc": 10500,
    "material": [ "steel" ],
    "symbol": "(",
    "color": "dark_gray",
    "//": "It can't fit the 9x18mm the Makarov uses because they're LIARS and it's actually 9.2mm.",
    "ammo": [ "357mag", "38", "38super", "380", "9mm" ],
    "dispersion": 320,
    "durability": 6,
    "blackpowder_tolerance": 56,
    "clip_size": 6,
    "reload": 350,
    "valid_mod_locations": [
      [ "barrel", 1 ],
      [ "bore", 1 ],
      [ "grip", 1 ],
      [ "mechanism", 4 ],
      [ "rail", 1 ],
      [ "sights", 1 ],
      [ "stock", 1 ],
      [ "underbarrel", 1 ]
    ],
    "pocket_data": [
      {
        "pocket_type": "MAGAZINE",
        "rigid": true,
        "ammo_restriction": { "357mag": 6, "38": 6, "38super": 6, "380": 6, "9mm": 6 },
        "allowed_speedloaders": [  ]
      }
    ],
    "melee_damage": { "bash": 8 }
  },
  {
    "id": "laugo_alien",
    "copy-from": "glock_17",
    "looks_like": "glock_17",
    "type": "GUN",
    "name": { "str": "competition pistol" },
    "description": "A rather recent introduction to the competition shooting market, this pistol has several innovations such as a non-reciprocating slide, a very low bore axis, and more, resulting in a highly accurate and reliable sidearm with little to no recoil. Good luck finding the magazines, though.",
    "variant_type": "gun",
    "variants": [
      {
        "id": "laugo_alien_iron",
        "name": { "str": "Laugo Alien" },
        "description": "A rather recent introduction to the competition shooting market, the Laugo Alien has several innovations such as a non-reciprocating slide, a very low bore axis, and more, resulting in a highly accurate and reliable sidearm with little to no recoil. Good luck finding the magazines, though.",
        "built_in_mods": "laugo_slide_iron"
      },
      {
        "id": "laugo_alien_reddot",
        "name": { "str": "Laugo Alien" },
        "description": "A rather recent introduction to the competition shooting market, the Laugo Alien has several innovations such as a non-reciprocating slide, a very low bore axis, and more, resulting in a highly accurate and reliable sidearm with little to no recoil. Good luck finding the magazines, though.",
        "built_in_mods": "laugo_slide_reddot"
      },
      {
        "id": "laugo_alien_picatinny",
        "name": { "str": "Laugo Alien" },
        "description": "A rather recent introduction to the competition shooting market, the Laugo Alien has several innovations such as a non-reciprocating slide, a very low bore axis, and more, resulting in a highly accurate and reliable sidearm with little to no recoil. Good luck finding the magazines, though.",
        "built_in_mods": "laugo_slide_picatinny"
      },
      {
        "id": "laugo_creator",
        "name": { "str": "Laugo Alien Creator 500" },
        "description": "A rather recent introduction to the competition shooting market, the Laugo Alien has several innovations such as a non-reciprocating slide, a very low bore axis, and more, resulting in a highly accurate and reliable sidearm with little to no recoil. This version has a 1911-style grip, as opposed to the Glock or Luger style of the original version.",
        "built_in_mods": "laugo_slide_reddot"
      }
    ],
    "weight": "1009 g",
    "volume": "292 ml",
    "longest_side": "210 mm",
    "barrel_length": "124 mm",
    "price": 700000,
    "price_postapoc": 8500,
    "to_hit": -1,
    "material": [ "steel" ],
    "//ammo": [ "9mm" ],
    "//": "The ammo is added with the sliders, so that the gun can be made unusable when stripped.",
    "valid_mod_locations": [
      [ "barrel", 1 ],
      [ "brass catcher", 1 ],
      [ "grip", 1 ],
      [ "mechanism", 4 ],
      [ "muzzle", 1 ],
      [ "rail", 1 ],
      [ "slide", 1 ],
      [ "stock", 1 ],
      [ "underbarrel", 1 ]
    ],
    "//2": "No sight slot, not by itself. The Alien has interchangeable slides instead.",
    "built_in_mods": "laugo_slide_iron",
    "ranged_damage": { "damage_type": "bullet", "amount": 0 },
    "dispersion": 320,
    "durability": 7,
    "blackpowder_tolerance": 36,
    "min_cycle_recoil": 340,
    "pocket_data": [ { "magazine_well": "250 ml", "pocket_type": "MAGAZINE_WELL", "item_restriction": [ "laugo_mag" ] } ],
    "melee_damage": { "bash": 10 }
  },
  {
    "id": "laugo_mag",
    "type": "MAGAZINE",
    "name": { "str": "Laugo Alien 17-round magazine" },
    "description": "Made for the Laugo Alien, this magazine holds 17 rounds.",
    "weight": "70 g",
    "volume": "75 ml",
    "longest_side": "111 mm",
    "price": 2900,
    "price_postapoc": 100,
    "material": [ "plastic", "steel" ],
    "symbol": "#",
    "color": "light_gray",
    "ammo_type": [ "9mm" ],
    "reload_time": 140,
    "flags": [ "MAG_COMPACT" ],
    "pocket_data": [ { "pocket_type": "MAGAZINE", "rigid": true, "ammo_restriction": { "9mm": 17 } } ]
  },
  {
    "id": "laugo_slide_iron",
    "type": "GUNMOD",
    "name": { "str": "Laugo Alien iron sight slide" },
    "description": "Uniquely, the Laugo Alien uses replaceable slides instead of a sight rail. This one contains basic iron sights.",
    "weight": "10 g",
    "volume": "10 ml",
    "longest_side": "120 mm",
    "integral_volume": "0 ml",
    "integral_weight": "0 g",
    "integral_longest_side": "0 cm",
    "price": 10000,
    "price_postapoc": 1000,
    "material": [ "steel" ],
    "symbol": ":",
    "color": "dark_gray",
    "location": "slide",
    "mod_targets": [ "laugo_alien" ],
    "install_time": "15 s",
    "ammo_modifier": [ "9mm" ],
    "min_skills": [ [ "weapon", 1 ] ],
    "add_mod": [ [ "sights mount" ] ]
  },
  {
    "id": "laugo_slide_reddot",
    "copy-from": "laugo_slide_iron",
    "type": "GUNMOD",
    "name": { "str": "Laugo Alien red dot sight slide" },
    "description": "Uniquely, the Laugo Alien uses replaceable slides instead of a sight rail. This one contains a sleek red dot sight.",
    "weight": "18 g",
    "volume": "15 ml",
    "longest_side": "120 mm",
    "integral_volume": "100 ml",
    "integral_weight": "100 g",
    "add_mod": [ [  ] ]
  },
  {
    "id": "laugo_slide_picatinny",
    "type": "GUNMOD",
    "name": { "str": "Laugo Alien custom rail slide" },
    "description": "Uniquely, the Laugo Alien uses replaceable slides instead of a sight rail. This one a Picatinny rail for attaching a normal sight, but no iron sights.",
    "weight": "13 g",
    "volume": "13 ml",
    "longest_side": "120 mm",
    "integral_volume": "33 ml",
    "integral_weight": "33 g",
    "integral_longest_side": "0 cm",
    "material": [ "steel" ],
    "add_mod": [ [ "sights" ] ]
  },
  {
    "id": "welrod",
    "copy-from": "pistol_base",
    "looks_like": "glock_17",
    "type": "GUN",
    "name": { "str": "bicycle pump" },
    "description": "A rather odd-looking bicycle pump that appears to have... iron sights? Something isn't right here.",
    "variants": [
      {
        "id": "welrod",
        "name": { "str": "Welrod 9mm Mk I" },
        "description": "An extremely bizarre looking gun, the Welrod was a clandestine, integrally-suppressed, bolt-action pistol utilized by British agents, featuring what is described best as a 'Hollywood quiet' level of noise when firing alongside a design which attempts to hide its true purpose."
      }
    ],
    "weight": "1235 g",
    "volume": "150 ml",
    "longest_side": "95 mm",
    "barrel_length": "83 mm",
    "price": 68000,
    "price_postapoc": 2500,
    "to_hit": -1,
    "material": [ "steel" ],
    "symbol": "(",
    "color": "dark_gray",
    "ammo": [ "9mm" ],
    "built_in_mods": "welsuppressor",
    "ranged_damage": { "damage_type": "bullet", "amount": -1 },
    "dispersion": 600,
    "durability": 6,
    "blackpowder_tolerance": 88,
    "min_cycle_recoil": 450,
    "flags": [ "ALLOWS_BODY_BLOCK" ],
    "weapon_category": [ "AUTOMATIC_PISTOLS" ],
    "pocket_data": [ { "magazine_well": "100 ml", "pocket_type": "MAGAZINE_WELL", "item_restriction": [ "welmag" ] } ],
    "melee_damage": { "bash": 7 }
  },
  {
    "id": "welmag",
    "type": "MAGAZINE",
    "name": { "str": "Welrod 9mm Mk I 6-round magazine" },
    "description": "The Welrod's design intentionally excludes a pistol grip, to improve concealability. As such, its magazines also function as a plastic grip.",
    "weight": "45 g",
    "volume": "40 ml",
    "longest_side": "40 mm",
    "price": 2900,
    "price_postapoc": 100,
    "material": [ "plastic", "steel" ],
    "symbol": "#",
    "color": "light_gray",
    "ammo_type": [ "9mm" ],
    "reload_time": 120,
    "flags": [ "MAG_COMPACT" ],
    "pocket_data": [ { "pocket_type": "MAGAZINE", "rigid": true, "ammo_restriction": { "9mm": 6 } } ]
  },
  {
    "id": "welsuppressor",
    "copy-from": "suppressor",
    "type": "GUNMOD",
    "name": { "str": "Welrod integrated suppressor" },
    "description": "The Welrod's suppressor effectively contains the entirety of the barrel inside, which makes the gun almost completely silent.",
    "weight": "0 g",
    "volume": "0 ml",
    "longest_side": "0 cm",
    "price": 0,
    "price_postapoc": 0,
    "material": [ "rubber" ],
    "consume_chance": 1,
    "consume_divisor": 600,
    "loudness_modifier": -75,
    "flags": [ "IRREMOVABLE" ],
    "melee_damage": { "bash": 3 }
  },
  {
    "id": "veterinary_pistol",
    "copy-from": "welrod",
    "looks_like": "glock_17",
    "type": "GUN",
    "name": { "str": "veterinary pistol" },
    "description": "An integrally silenced .45 ACP pistol that fits 1911 magazines. Designed to put down animals (or zombies) quickly, painlessly, and soundlessly.",
    "variants": [
      {
        "id": "veterinary_pistol",
        "name": { "str": "Station SIX-45 veterinary pistol" },
        "description": "An integrally silenced .45 ACP pistol that fits 1911 magazines. Designed to put down animals (or zombies) quickly, painlessly, and soundlessly. Originally made in 9mm in Old England, it was later imported into the US and made to fit its pistol regulations as the Station SIX-9 and SIX-45."
      }
    ],
    "weight": "940 g",
    "volume": "350 ml",
    "longest_side": "285 mm",
    "barrel_length": "165 mm",
    "price": 38000,
    "price_postapoc": 9000,
    "ammo": [ "45" ],
    "built_in_mods": "vetsuppressor",
    "ranged_damage": { "damage_type": "bullet", "amount": -2 },
    "dispersion": 600,
    "durability": 8,
    "pocket_data": [ { "magazine_well": "250 ml", "pocket_type": "MAGAZINE_WELL", "item_restriction": [ "m1911mag", "m1911bigmag" ] } ]
  }
]
